polidoro_table/__init__.py
polidoro_table/borders.py
polidoro_table/cell.py
polidoro_table/column.py
polidoro_table/property.py
polidoro_table/row.py
polidoro_table/string_utils.py
polidoro_table/table.py
polidoro_table-1.1.0.dist-info/LICENSE
polidoro_table-1.1.0.dist-info/METADATA
polidoro_table-1.1.0.dist-info/WHEEL
polidoro_table-1.1.0.dist-info/top_level.txt
polidoro_table-1.1.0.dist-info/RECORD
